pyproject.toml
setup.cfg
./CleanEmonCore/CouchDBAdapter.py
./CleanEmonCore/__init__.py
./CleanEmonCore/__main__.py
./CleanEmonCore/dotfiles.py
./CleanEmonCore/models.py
./CleanEmonCore/Events/__init__.py
./CleanEmonCore/Events/builtins.py
./CleanEmonCore/Events/events.py
./CleanEmonCore/tests/__init__.py
./CleanEmonCore/tests/test_CouchDBAdapter.py
./CleanEmonCore/tests/test_models.py
./CleanEmonCore/tests/Events/__init__.py
./CleanEmonCore/tests/Events/test_builtins.py
CleanEmon_Core.egg-info/PKG-INFO
CleanEmon_Core.egg-info/SOURCES.txt
CleanEmon_Core.egg-info/dependency_links.txt
CleanEmon_Core.egg-info/requires.txt
CleanEmon_Core.egg-info/top_level.txt