Metadata-Version: 2.1
Name: CleanEmon-Core
Version: 0.4
Summary: The core library used by the CleanEmon ecosystem
Author: George Vasiliadis
Author-email: geor.vasiliadis@gmail.com
Requires-Python: >=3.6
